aresxq/__init__.py
aresxq-1.0.1.dist-info/licenses/LICENSE
aresxq-1.0.1.dist-info/METADATA
aresxq-1.0.1.dist-info/WHEEL
aresxq-1.0.1.dist-info/top_level.txt
aresxq-1.0.1.dist-info/RECORD
