Metadata-Version: 2.4
Name: aresxq
Version: 1.0.1
Summary: ARES-X/Q: Quantum-safe encryption with ARX cipher, Kyber-style KEM, and AEAD
Home-page: https://github.com/fb6si15/aresxq
Author: Joaquin Martinez
Author-email: your@email.com
License: MIT
Classifier: Programming Language :: Python :: 3
Classifier: License :: OSI Approved :: MIT License
Classifier: Operating System :: OS Independent
Classifier: Development Status :: 4 - Beta
Classifier: Intended Audience :: Developers
Classifier: Topic :: Security :: Cryptography
Requires-Python: >=3.7
License-File: LICENSE
Requires-Dist: pycryptodome
Dynamic: author
Dynamic: author-email
Dynamic: classifier
Dynamic: description
Dynamic: description-content-type
Dynamic: home-page
Dynamic: license
Dynamic: license-file
Dynamic: requires-dist
Dynamic: requires-python
Dynamic: summary
